README.md
setup.cfg
setup.py
zdk/__init__.py
zdk.egg-info/PKG-INFO
zdk.egg-info/SOURCES.txt
zdk.egg-info/dependency_links.txt
zdk.egg-info/top_level.txt
zdk/core/__init__.py
zdk/core/clients.py
zdk/core/factory.py
zdk/core/serializers.py
zdk/zinobe/zevents/__init__.py
zdk/zinobe/zevents/client.py
zdk/zinobe/zevents/exceptions.py
zdk/zinobe/zevents/helpers.py
zdk/zinobe/zevents/process.py
zdk/zinobe/zevents/serializer.py